example_envs/__init__.py
example_envs/dummy_env/__init__.py
example_envs/dummy_env/test_step.cu
example_envs/dummy_env/test_step_numba.py
example_envs/dummy_env/tutorial_basics.py
example_envs/single_agent/__init__.py
example_envs/single_agent/base.py
example_envs/single_agent/classic_control/__init__.py
example_envs/single_agent/classic_control/acrobot/acrobot.py
example_envs/single_agent/classic_control/acrobot/acrobot_step_numba.py
example_envs/single_agent/classic_control/cartpole/__init__.py
example_envs/single_agent/classic_control/cartpole/cartpole.py
example_envs/single_agent/classic_control/cartpole/cartpole_step_numba.py
example_envs/single_agent/classic_control/continuous_mountain_car/continuous_mountain_car.py
example_envs/single_agent/classic_control/continuous_mountain_car/continuous_mountain_car_step_numba.py
example_envs/single_agent/classic_control/mountain_car/mountain_car.py
example_envs/single_agent/classic_control/mountain_car/mountain_car_step_numba.py
example_envs/single_agent/classic_control/pendulum/pendulum.py
example_envs/single_agent/classic_control/pendulum/pendulum_step_numba.py
example_envs/tag_continuous/__init__.py
example_envs/tag_continuous/generate_rollout_animation.py
example_envs/tag_continuous/tag_continuous.py
example_envs/tag_continuous/tag_continuous_step_numba.py
example_envs/tag_continuous/tag_continuous_step_pycuda.cu
example_envs/tag_gridworld/__init__.py
example_envs/tag_gridworld/tag_gridworld.py
example_envs/tag_gridworld/tag_gridworld_step_numba.py
example_envs/tag_gridworld/tag_gridworld_step_pycuda.cu
tests/__init__.py
tests/example_envs/__init__.py
tests/example_envs/numba_tests/__init__.py
tests/example_envs/numba_tests/test_tag_continuous.py
tests/example_envs/numba_tests/test_tag_gridworld.py
tests/example_envs/numba_tests/single_agent/classic_control/test_acrobot.py
tests/example_envs/numba_tests/single_agent/classic_control/test_cartpole.py
rl_warp_drive-2.7.1.dist-info/LICENSE.txt
rl_warp_drive-2.7.1.dist-info/METADATA
rl_warp_drive-2.7.1.dist-info/WHEEL
rl_warp_drive-2.7.1.dist-info/top_level.txt
rl_warp_drive-2.7.1.dist-info/RECORD
