Metadata-Version: 2.1
Name: rl-warp-drive
Version: 2.7.1
Summary: Framework for fast end-to-end multi-agent reinforcement learning on GPUs.
Home-page: https://github.com/salesforce/warp-drive
Author: Tian Lan, Sunil Srinivasa, Brenton Chu, Stephan Zheng
Author-email: tian.lan@salesforce.com
License: UNKNOWN
Platform: UNKNOWN
Classifier: Programming Language :: Python :: 3
Classifier: Environment :: GPU :: NVIDIA CUDA :: 11.0
Classifier: License :: OSI Approved :: BSD License
Classifier: Operating System :: OS Independent
Requires-Python: >=3.7.0
Requires-Dist: gym (>=0.26)
Requires-Dist: matplotlib (>=3.2.1)
Requires-Dist: numpy (>=1.18.1)
Requires-Dist: pycuda (>=2022.1)
Requires-Dist: pytest (>=6.1.0)
Requires-Dist: pyyaml (>=5.4)
Requires-Dist: torch (>=1.9)
Requires-Dist: numba (>=0.54.0)
